{
  "$schema": "../gen/schemas/desktop-schema.json",
  "identifier": "default",
  "description": "Capability for the main window",
  "windows": ["main", "window-*"],
  "permissions": [
    "core:default",
    "core:menu:default",
    "core:window:allow-create",
    "core:window:allow-is-fullscreen",
    "core:window:allow-set-fullscreen",
    "core:window:allow-set-size",
    "core:webview:allow-create-webview-window",
    "opener:default",
    "fs:allow-read-file",
    "fs:allow-appdata-read-recursive",
    "fs:allow-appdata-write-recursive"
  ]
}
